{
  "relatedCats": "英杰 一帆", 
  "name": "杰希",
  "addPhotoNumber": "0",
  "furColor": "黑狸加白",
  "classification": "狸花",
  "gender": "母",
  "status": "送养",
  "isSterilization": "已绝育",
  "sterilizationTime": "2017秋",
  "appearance": "大小眼 白多",
  "character": "亲人不可抱 可摸",
  "firstSightingTime": "2016冬",
  "relationship": "英杰和一帆的母亲；同居猫：果冻",
  "deliveryTime": "2020-05",
  "audioNumber": "0"
}
{
  "relatedCats": "杰希 一帆", 
  "name": "英杰",
  "addPhotoNumber": "3",
  "furColor": "长毛奶牛",
  "classification": "奶牛",
  "gender": "母",
  "status": "健康",
  "isSterilization": "已绝育",
  "sterilizationTime": "2018夏",
  "appearance": "好看的长毛奶牛 白多 小胡子",
  "character": "薛定谔亲人",
  "firstSightingTime": "2017春",
  "relationship": "杰希之女，和一帆一窝",
  "audioNumber": "1"
}
{
  "relatedCats": "杰希 英杰", 
  "name": "一帆",
  "addPhotoNumber": "0",
  "furColor": "奶牛",
  "classification": "奶牛",
  "gender": "公",
  "status": "健康",
  "isSterilization": "已绝育",
  "sterilizationTime": "2019-12-05",
  "appearance": "无情的警长",
  "character": "薛定谔亲人",
  "firstSightingTime": "2017春",
  "relationship": "杰希之子，和英杰一窝；曾经和小黄鸭、鸡米花关系好，之后和奶酪一起过，后与银桂、绯云有复杂的三角关系，曾和绯云一起找卡皮巴拉切磋武力，目前和蒜香鸡感情升温中。",
  "audioNumber": "0"
}
{
  "relatedCats": "杰希", 
  "name": "土谦",
  "addPhotoNumber": "0",
  "furColor": "黑狸加白",
  "classification": "狸花",
  "gender": "公",
  "status": "送养",
  "isSterilization": "已绝育",
  "sterilizationTime": "2018-11-28",
  "appearance": "白多 2018年尾突然亲人",
  "character": "亲人可抱",
  "firstSightingTime": "2018秋 ",
  "relationship": "与杰希一家关系好",
  "deliveryTime": "2019-07",
  "audioNumber": "0"
}
